derek/__init__.py
derek/_derek.py
derek/_parse/__init__.py
derek/_parse/_oas2.py
derek/_parse/_Parser.py
derek/_typing.py
derek_py-0.0.2.dist-info/LICENSE
derek_py-0.0.2.dist-info/WHEEL
derek_py-0.0.2.dist-info/METADATA
derek_py-0.0.2.dist-info/RECORD
