Metadata-Version: 2.1
Name: derek-py
Version: 0.0.2
Summary: Convert data structure to schema.
Home-page: https://github.com/benjaminwoods/derek
License: MIT
Keywords: data,schema,convert,analyze
Author: Benjamin Woods
Author-email: ben@bjqw.me
Requires-Python: >=3.6,<3.10
Classifier: Development Status :: 2 - Pre-Alpha
Classifier: Intended Audience :: Developers
Classifier: License :: OSI Approved :: MIT License
Classifier: Natural Language :: English
Classifier: Operating System :: OS Independent
Classifier: Programming Language :: Python :: 3
Classifier: Programming Language :: Python :: 3.6
Classifier: Programming Language :: Python :: 3.7
Classifier: Programming Language :: Python :: 3.8
Classifier: Programming Language :: Python :: 3.9
Classifier: Programming Language :: Python :: 3.6
Classifier: Programming Language :: Python :: 3.7
Classifier: Programming Language :: Python :: 3.8
Classifier: Programming Language :: Python :: 3.9
Classifier: Topic :: Database
Project-URL: Repository, https://github.com/benjaminwoods/derek
